{"help": "Return the metadata of a dataset (package) and its resources.\n\n    :param id: the id or name of the dataset\n    :type id: string\n    :param use_default_schema: use default package schema instead of\n        a custom schema defined with an IDatasetForm plugin (default: False)\n    :type use_default_schema: bool\n\n    :rtype: dictionary\n\n    ", "success": true, "result": {"license_title": null, "maintainer": null, "temporal_coverage-from": "[]", "relationships_as_object": [], "data_dict": "{\"license_title\": null, \"maintainer\": null, \"relationships_as_object\": [], \"private\": false, \"maintainer_email\": null, \"revision_timestamp\": \"2015-02-10T14:40:05.686705\", \"id\": \"b1f2f7be-d024-425f-b6ff-5d8f45d86738\", \"metadata_created\": \"2015-02-10T14:40:05.686705\", \"metadata_modified\": \"2015-02-10T14:40:05.708276\", \"author\": null, \"author_email\": null, \"state\": \"active\", \"version\": null, \"creator_user_id\": \"60e687bf-a6d8-43e2-a50e-efab84b27952\", \"type\": \"dataset\", \"resources\": [{\"resource_group_id\": \"1453b239-c698-4d94-9350-ed2a05839d9a\", \"verified_date\": \"2015-02-10T14:40:05.328921\", \"cache_last_updated\": null, \"revision_timestamp\": \"2015-02-10T14:40:05.686705\", \"webstore_last_updated\": null, \"id\": \"da6e91fe-4fe7-4442-9382-4ac5a402bada\", \"size\": null, \"verified\": \"True\", \"state\": \"active\", \"last_modified\": null, \"hash\": \"\", \"description\": \"Resource locator\", \"format\": \"wms\", \"tracking_summary\": {\"total\": 0, \"recent\": 0}, \"mimetype_inner\": null, \"url_type\": null, \"resource_locator_protocol\": \"\", \"mimetype\": null, \"cache_url\": null, \"name\": \"INSPIRE View Service\", \"created\": \"2015-02-10T14:40:05.752325\", \"url\": \"http://inspire.misoportal.com/geoserver/adur_and_worthing_council_allotments/wms?request=getCapabilities\", \"wms_base_urls\": \"http://inspire.misoportal.com:80/geoserver/adur_and_worthing_council_allotments/ows\", \"webstore_url\": null, \"resource_locator_function\": \"information\", \"ckan_recommended_wms_preview\": \"True\", \"position\": 0, \"revision_id\": \"e1fb3ea3-44b2-4dc0-94f6-b09e828142d2\", \"resource_type\": null}, {\"resource_group_id\": \"1453b239-c698-4d94-9350-ed2a05839d9a\", \"cache_last_updated\": null, \"revision_timestamp\": \"2015-02-10T14:40:05.686705\", \"webstore_last_updated\": null, \"id\": \"8aeee900-3a8a-4f8c-b636-162886a43e2a\", \"size\": null, \"state\": \"active\", \"last_modified\": null, \"hash\": \"\", \"description\": \"Resource locator\", \"format\": \"\", \"tracking_summary\": {\"total\": 0, \"recent\": 0}, \"mimetype_inner\": null, \"url_type\": null, \"resource_locator_protocol\": \"\", \"mimetype\": null, \"cache_url\": null, \"name\": \"INSPIRE Download Service\", \"created\": \"2015-02-10T14:40:05.752341\", \"url\": \"http://inspire.misoportal.com/geoserver/adur_and_worthing_council_allotments/wfs?service=wfs&version=2.0.0&request=GetCapabilities\", \"webstore_url\": null, \"resource_locator_function\": \"download\", \"position\": 1, \"revision_id\": \"e1fb3ea3-44b2-4dc0-94f6-b09e828142d2\", \"resource_type\": null}], \"num_resources\": 2, \"tags\": [{\"vocabulary_id\": null, \"display_name\": \"allotments\", \"name\": \"allotments\", \"revision_timestamp\": \"2015-02-10T14:40:05.686705\", \"state\": \"active\", \"id\": \"dc363823-fe1d-4256-9bc4-52104e1bde9a\"}, {\"vocabulary_id\": null, \"display_name\": \"land-use\", \"name\": \"land-use\", \"revision_timestamp\": \"2015-02-10T14:40:05.686705\", \"state\": \"active\", \"id\": \"499963be-c276-44f8-9c62-3fb8aa9e9bd6\"}], \"tracking_summary\": {\"total\": 0, \"recent\": 0}, \"groups\": [], \"license_id\": null, \"relationships_as_subject\": [], \"num_tags\": 2, \"organization\": {\"description\": \"\", \"title\": \"Adur District Council\", \"created\": \"2014-09-08T13:58:54.660044\", \"approval_status\": \"pending\", \"revision_timestamp\": \"2014-09-08T12:58:54.608955\", \"is_organization\": true, \"state\": \"active\", \"image_url\": \"\", \"revision_id\": \"bcaec468-9f33-4631-87f3-060526e7ee9d\", \"type\": \"organization\", \"id\": \"58011ef9-29dc-4729-86e6-82b86d5376ba\", \"name\": \"adur-district-council\"}, \"name\": \"allotments46\", \"isopen\": false, \"url\": null, \"notes\": \"Location of Allotments within Adur District and Worthing Borough\", \"owner_org\": \"58011ef9-29dc-4729-86e6-82b86d5376ba\", \"extras\": [{\"state\": \"active\", \"value\": \"True\", \"revision_timestamp\": \"2015-02-10T14:40:05.686705\", \"package_id\": \"b1f2f7be-d024-425f-b6ff-5d8f45d86738\", \"key\": \"UKLP\", \"revision_id\": \"e1fb3ea3-44b2-4dc0-94f6-b09e828142d2\", \"id\": \"fc31535b-7676-4390-9f80-68718c1ed883\"}, {\"state\": \"active\", \"value\": \"[\\\"Limited by Public Sector Mapping Agreement.\\\"]\", \"revision_timestamp\": \"2015-02-10T14:40:05.686705\", \"package_id\": \"b1f2f7be-d024-425f-b6ff-5d8f45d86738\", \"key\": \"access_constraints\", \"revision_id\": \"e1fb3ea3-44b2-4dc0-94f6-b09e828142d2\", \"id\": \"2b20f090-2856-4229-904c-16892934c989\"}, {\"state\": \"active\", \"value\": \"-0.222355168468641\", \"revision_timestamp\": \"2015-02-10T14:40:05.686705\", \"package_id\": \"b1f2f7be-d024-425f-b6ff-5d8f45d86738\", \"key\": \"bbox-east-long\", \"revision_id\": \"e1fb3ea3-44b2-4dc0-94f6-b09e828142d2\", \"id\": \"dc82c275-668a-47a4-8268-bfc0bfc1a7dc\"}, {\"state\": \"active\", \"value\": \"50.8437840950851\", \"revision_timestamp\": \"2015-02-10T14:40:05.686705\", \"package_id\": \"b1f2f7be-d024-425f-b6ff-5d8f45d86738\", \"key\": \"bbox-north-lat\", \"revision_id\": \"e1fb3ea3-44b2-4dc0-94f6-b09e828142d2\", \"id\": \"0d10695f-6ca7-476d-b751-fb53ae16c5a5\"}, {\"state\": \"active\", \"value\": \"50.817007994021\", \"revision_timestamp\": \"2015-02-10T14:40:05.686705\", \"package_id\": \"b1f2f7be-d024-425f-b6ff-5d8f45d86738\", \"key\": \"bbox-south-lat\", \"revision_id\": \"e1fb3ea3-44b2-4dc0-94f6-b09e828142d2\", \"id\": \"8f2d6e10-d8a7-4235-b1ae-e4240344fe83\"}, {\"state\": \"active\", \"value\": \"-0.434271074180314\", \"revision_timestamp\": \"2015-02-10T14:40:05.686705\", \"package_id\": \"b1f2f7be-d024-425f-b6ff-5d8f45d86738\", \"key\": \"bbox-west-long\", \"revision_id\": \"e1fb3ea3-44b2-4dc0-94f6-b09e828142d2\", \"id\": \"81964ea6-9a59-4a79-a6f3-a59e6c8c756e\"}, {\"state\": \"active\", \"value\": \"GIS@adur-worthing.gov.uk\", \"revision_timestamp\": \"2015-02-10T14:40:05.686705\", \"package_id\": \"b1f2f7be-d024-425f-b6ff-5d8f45d86738\", \"key\": \"contact-email\", \"revision_id\": \"e1fb3ea3-44b2-4dc0-94f6-b09e828142d2\", \"id\": \"6592e29f-73ee-4db7-a82b-aa1c0a88b96d\"}, {\"state\": \"active\", \"value\": \"[]\", \"revision_timestamp\": \"2015-02-10T14:40:05.686705\", \"package_id\": \"b1f2f7be-d024-425f-b6ff-5d8f45d86738\", \"key\": \"coupled-resource\", \"revision_id\": \"e1fb3ea3-44b2-4dc0-94f6-b09e828142d2\", \"id\": \"5a4de3fd-7a3d-4bfb-9bf6-e37630c6dc01\"}, {\"state\": \"active\", \"value\": \"[{\\\"type\\\": \\\"revision\\\", \\\"value\\\": \\\"2015-02-10\\\"}]\", \"revision_timestamp\": \"2015-02-10T14:40:05.686705\", \"package_id\": \"b1f2f7be-d024-425f-b6ff-5d8f45d86738\", \"key\": \"dataset-reference-date\", \"revision_id\": \"e1fb3ea3-44b2-4dc0-94f6-b09e828142d2\", \"id\": \"e45d14d0-e851-489f-9ef1-fea26f6e9821\"}, {\"state\": \"active\", \"value\": \"asNeeded\", \"revision_timestamp\": \"2015-02-10T14:40:05.686705\", \"package_id\": \"b1f2f7be-d024-425f-b6ff-5d8f45d86738\", \"key\": \"frequency-of-update\", \"revision_id\": \"e1fb3ea3-44b2-4dc0-94f6-b09e828142d2\", \"id\": \"4ddb1bfc-f3e3-4a00-9a03-24645688a6e3\"}, {\"state\": \"active\", \"value\": \"25361192-b257-4b8b-9cb0-8dc80b3626ba\", \"revision_timestamp\": \"2015-02-10T14:40:05.686705\", \"package_id\": \"b1f2f7be-d024-425f-b6ff-5d8f45d86738\", \"key\": \"guid\", \"revision_id\": \"e1fb3ea3-44b2-4dc0-94f6-b09e828142d2\", \"id\": \"cd0a56d6-a4bb-4b6a-b41e-65bad367172f\"}, {\"state\": \"active\", \"value\": \"d9c77a1e-4573-4ccf-80f4-dcd4e023bffe\", \"revision_timestamp\": \"2015-02-10T14:40:05.686705\", \"package_id\": \"b1f2f7be-d024-425f-b6ff-5d8f45d86738\", \"key\": \"harvest_object_id\", \"revision_id\": \"e1fb3ea3-44b2-4dc0-94f6-b09e828142d2\", \"id\": \"bc77aad6-4a27-4f50-8a60-ba920acc62c2\"}, {\"state\": \"active\", \"value\": \"http://inspire.misoportal.com/metadata/files/Adur_and_Worthing_Council/adur_allotments.xml\", \"revision_timestamp\": \"2015-02-10T14:40:05.686705\", \"package_id\": \"b1f2f7be-d024-425f-b6ff-5d8f45d86738\", \"key\": \"harvest_source_reference\", \"revision_id\": \"e1fb3ea3-44b2-4dc0-94f6-b09e828142d2\", \"id\": \"673d686d-b010-4637-84d1-2caf9aca1332\"}, {\"state\": \"active\", \"value\": \"harvest\", \"revision_timestamp\": \"2015-02-10T14:40:05.686705\", \"package_id\": \"b1f2f7be-d024-425f-b6ff-5d8f45d86738\", \"key\": \"import_source\", \"revision_id\": \"e1fb3ea3-44b2-4dc0-94f6-b09e828142d2\", \"id\": \"847d5f05-02bf-4372-b2b3-fc7131edce80\"}, {\"state\": \"active\", \"value\": \"[\\\"geossNonCommercial\\\", \\\"(e) intellectual property rights\\\", \\\"no limitation\\\"]\", \"revision_timestamp\": \"2015-02-10T14:40:05.686705\", \"package_id\": \"b1f2f7be-d024-425f-b6ff-5d8f45d86738\", \"key\": \"licence\", \"revision_id\": \"e1fb3ea3-44b2-4dc0-94f6-b09e828142d2\", \"id\": \"00252dea-a771-41e2-b108-0b583448b130\"}, {\"state\": \"active\", \"value\": \"2015-02-10\", \"revision_timestamp\": \"2015-02-10T14:40:05.686705\", \"package_id\": \"b1f2f7be-d024-425f-b6ff-5d8f45d86738\", \"key\": \"metadata-date\", \"revision_id\": \"e1fb3ea3-44b2-4dc0-94f6-b09e828142d2\", \"id\": \"d2d676dc-3569-436a-b86d-150cc3ad870d\"}, {\"state\": \"active\", \"value\": \"eng\", \"revision_timestamp\": \"2015-02-10T14:40:05.686705\", \"package_id\": \"b1f2f7be-d024-425f-b6ff-5d8f45d86738\", \"key\": \"metadata-language\", \"revision_id\": \"e1fb3ea3-44b2-4dc0-94f6-b09e828142d2\", \"id\": \"2f1618e3-847a-49c4-8932-bbfcf37e22e6\"}, {\"state\": \"active\", \"value\": \"\", \"revision_timestamp\": \"2015-02-10T14:40:05.686705\", \"package_id\": \"b1f2f7be-d024-425f-b6ff-5d8f45d86738\", \"key\": \"provider\", \"revision_id\": \"e1fb3ea3-44b2-4dc0-94f6-b09e828142d2\", \"id\": \"a80208a1-d383-40ad-b299-60c03388f4fc\"}, {\"state\": \"active\", \"value\": \"dataset\", \"revision_timestamp\": \"2015-02-10T14:40:05.686705\", \"package_id\": \"b1f2f7be-d024-425f-b6ff-5d8f45d86738\", \"key\": \"resource-type\", \"revision_id\": \"e1fb3ea3-44b2-4dc0-94f6-b09e828142d2\", \"id\": \"df7e4536-7a72-436d-ad76-e5284c0640e4\"}, {\"state\": \"active\", \"value\": \"Adur District and Worthing Borough Councils (pointOfContact)\", \"revision_timestamp\": \"2015-02-10T14:40:05.686705\", \"package_id\": \"b1f2f7be-d024-425f-b6ff-5d8f45d86738\", \"key\": \"responsible-party\", \"revision_id\": \"e1fb3ea3-44b2-4dc0-94f6-b09e828142d2\", \"id\": \"f7a152de-a339-4e84-9a69-ee900eaf1788\"}, {\"state\": \"active\", \"value\": \"{\\\"type\\\":\\\"Polygon\\\",\\\"coordinates\\\":[[[-0.222355168468641, 50.817007994021],[-0.222355168468641, 50.8437840950851], [-0.434271074180314, 50.8437840950851], [-0.434271074180314, 50.817007994021], [-0.222355168468641, 50.817007994021]]]}\", \"revision_timestamp\": \"2015-02-10T14:40:05.686705\", \"package_id\": \"b1f2f7be-d024-425f-b6ff-5d8f45d86738\", \"key\": \"spatial\", \"revision_id\": \"e1fb3ea3-44b2-4dc0-94f6-b09e828142d2\", \"id\": \"996df7fa-cd2e-4a5d-b7ea-cc31d182be2d\"}, {\"state\": \"active\", \"value\": \"\", \"revision_timestamp\": \"2015-02-10T14:40:05.686705\", \"package_id\": \"b1f2f7be-d024-425f-b6ff-5d8f45d86738\", \"key\": \"spatial-data-service-type\", \"revision_id\": \"e1fb3ea3-44b2-4dc0-94f6-b09e828142d2\", \"id\": \"724ed8b9-29bb-4407-aa92-0634af31f436\"}, {\"state\": \"active\", \"value\": \"\", \"revision_timestamp\": \"2015-02-10T14:40:05.686705\", \"package_id\": \"b1f2f7be-d024-425f-b6ff-5d8f45d86738\", \"key\": \"spatial-reference-system\", \"revision_id\": \"e1fb3ea3-44b2-4dc0-94f6-b09e828142d2\", \"id\": \"8ef19f45-e4c5-4945-b4d1-c8254b35d989\"}, {\"state\": \"active\", \"value\": \"[]\", \"revision_timestamp\": \"2015-02-10T14:40:05.686705\", \"package_id\": \"b1f2f7be-d024-425f-b6ff-5d8f45d86738\", \"key\": \"temporal_coverage-from\", \"revision_id\": \"e1fb3ea3-44b2-4dc0-94f6-b09e828142d2\", \"id\": \"84c3ac74-2473-4dc3-b508-26a9a083edf5\"}, {\"state\": \"active\", \"value\": \"[]\", \"revision_timestamp\": \"2015-02-10T14:40:05.686705\", \"package_id\": \"b1f2f7be-d024-425f-b6ff-5d8f45d86738\", \"key\": \"temporal_coverage-to\", \"revision_id\": \"e1fb3ea3-44b2-4dc0-94f6-b09e828142d2\", \"id\": \"c4ca2cd3-5740-4b00-add8-665ff3767a16\"}, {\"state\": \"active\", \"value\": \"Towns & Cities\", \"revision_timestamp\": \"2015-03-16T18:10:08.802815\", \"package_id\": \"b1f2f7be-d024-425f-b6ff-5d8f45d86738\", \"key\": \"theme-primary\", \"revision_id\": \"fc2b6630-84f8-4c88-8ac7-0ca275b2bc97\", \"id\": \"77d8ce2e-3141-4dbf-992a-3af069deb520\"}, {\"state\": \"active\", \"value\": \"[\\\"Business & Economy\\\"]\", \"revision_timestamp\": \"2015-03-16T18:10:08.802815\", \"package_id\": \"b1f2f7be-d024-425f-b6ff-5d8f45d86738\", \"key\": \"theme-secondary\", \"revision_id\": \"fc2b6630-84f8-4c88-8ac7-0ca275b2bc97\", \"id\": \"65f4d855-14f2-4991-af1f-bed302a30f39\"}], \"title\": \"Allotments\", \"revision_id\": \"e1fb3ea3-44b2-4dc0-94f6-b09e828142d2\"}", "private": false, "maintainer_email": null, "num_tags": 2, "id": "b1f2f7be-d024-425f-b6ff-5d8f45d86738", "metadata_created": "2015-02-10T14:40:05.686705", "metadata_modified": "2015-02-10T14:40:05.708276", "author": null, "author_email": null, "state": "active", "version": null, "temporal_coverage-to": "[]", "license_id": null, "type": "dataset", "resources": [{"verified_date": "2015-02-10T14:40:05.328921", "hash": "", "description": "Resource locator", "created": "2015-02-10T14:40:05.752325", "url": "http://inspire.misoportal.com/geoserver/adur_and_worthing_council_allotments/wms?request=getCapabilities", "format": "wms", "verified": "True", "tracking_summary": {"total": 0, "recent": 0}, "resource_locator_function": "information", "resource_locator_protocol": "", "ckan_recommended_wms_preview": "True", "position": 0, "revision_id": "e1fb3ea3-44b2-4dc0-94f6-b09e828142d2", "wms_base_urls": "http://inspire.misoportal.com:80/geoserver/adur_and_worthing_council_allotments/ows", "id": "da6e91fe-4fe7-4442-9382-4ac5a402bada", "name": "INSPIRE View Service"}, {"hash": "", "description": "Resource locator", "created": "2015-02-10T14:40:05.752341", "url": "http://inspire.misoportal.com/geoserver/adur_and_worthing_council_allotments/wfs?service=wfs&version=2.0.0&request=GetCapabilities", "format": "", "tracking_summary": {"total": 0, "recent": 0}, "resource_locator_function": "download", "resource_locator_protocol": "", "position": 1, "revision_id": "e1fb3ea3-44b2-4dc0-94f6-b09e828142d2", "id": "8aeee900-3a8a-4f8c-b636-162886a43e2a", "name": "INSPIRE Download Service"}], "num_resources": 2, "contact-email": "GIS@adur-worthing.gov.uk", "tags": [{"vocabulary_id": null, "display_name": "allotments", "name": "allotments", "revision_timestamp": "2015-02-10T14:40:05.686705", "state": "active", "id": "dc363823-fe1d-4256-9bc4-52104e1bde9a"}, {"vocabulary_id": null, "display_name": "land-use", "name": "land-use", "revision_timestamp": "2015-02-10T14:40:05.686705", "state": "active", "id": "499963be-c276-44f8-9c62-3fb8aa9e9bd6"}], "tracking_summary": {"total": 0, "recent": 0}, "groups": [], "creator_user_id": "60e687bf-a6d8-43e2-a50e-efab84b27952", "relationships_as_subject": [], "revision_timestamp": "2015-02-10T14:40:05.686705", "organization": {"description": "", "created": "2014-09-08T13:58:54.660044", "title": "Adur District Council", "name": "adur-district-council", "revision_timestamp": "2014-09-08T12:58:54.608955", "is_organization": true, "state": "active", "image_url": "", "revision_id": "bcaec468-9f33-4631-87f3-060526e7ee9d", "type": "organization", "id": "58011ef9-29dc-4729-86e6-82b86d5376ba", "approval_status": "pending"}, "name": "allotments46", "isopen": false, "url": null, "notes": "Location of Allotments within Adur District and Worthing Borough", "owner_org": "58011ef9-29dc-4729-86e6-82b86d5376ba", "theme-secondary": "[\"Business & Economy\"]", "extras": [{"package_id": "b1f2f7be-d024-425f-b6ff-5d8f45d86738", "value": "True", "revision_timestamp": "2015-02-10T14:40:05.686705", "state": "active", "key": "UKLP", "revision_id": "e1fb3ea3-44b2-4dc0-94f6-b09e828142d2", "id": "fc31535b-7676-4390-9f80-68718c1ed883"}, {"package_id": "b1f2f7be-d024-425f-b6ff-5d8f45d86738", "value": "[\"Limited by Public Sector Mapping Agreement.\"]", "revision_timestamp": "2015-02-10T14:40:05.686705", "state": "active", "key": "access_constraints", "revision_id": "e1fb3ea3-44b2-4dc0-94f6-b09e828142d2", "id": "2b20f090-2856-4229-904c-16892934c989"}, {"package_id": "b1f2f7be-d024-425f-b6ff-5d8f45d86738", "value": "-0.222355168468641", "revision_timestamp": "2015-02-10T14:40:05.686705", "state": "active", "key": "bbox-east-long", "revision_id": "e1fb3ea3-44b2-4dc0-94f6-b09e828142d2", "id": "dc82c275-668a-47a4-8268-bfc0bfc1a7dc"}, {"package_id": "b1f2f7be-d024-425f-b6ff-5d8f45d86738", "value": "50.8437840950851", "revision_timestamp": "2015-02-10T14:40:05.686705", "state": "active", "key": "bbox-north-lat", "revision_id": "e1fb3ea3-44b2-4dc0-94f6-b09e828142d2", "id": "0d10695f-6ca7-476d-b751-fb53ae16c5a5"}, {"package_id": "b1f2f7be-d024-425f-b6ff-5d8f45d86738", "value": "50.817007994021", "revision_timestamp": "2015-02-10T14:40:05.686705", "state": "active", "key": "bbox-south-lat", "revision_id": "e1fb3ea3-44b2-4dc0-94f6-b09e828142d2", "id": "8f2d6e10-d8a7-4235-b1ae-e4240344fe83"}, {"package_id": "b1f2f7be-d024-425f-b6ff-5d8f45d86738", "value": "-0.434271074180314", "revision_timestamp": "2015-02-10T14:40:05.686705", "state": "active", "key": "bbox-west-long", "revision_id": "e1fb3ea3-44b2-4dc0-94f6-b09e828142d2", "id": "81964ea6-9a59-4a79-a6f3-a59e6c8c756e"}, {"package_id": "b1f2f7be-d024-425f-b6ff-5d8f45d86738", "value": "GIS@adur-worthing.gov.uk", "revision_timestamp": "2015-02-10T14:40:05.686705", "state": "active", "key": "contact-email", "revision_id": "e1fb3ea3-44b2-4dc0-94f6-b09e828142d2", "id": "6592e29f-73ee-4db7-a82b-aa1c0a88b96d"}, {"package_id": "b1f2f7be-d024-425f-b6ff-5d8f45d86738", "value": "[]", "revision_timestamp": "2015-02-10T14:40:05.686705", "state": "active", "key": "coupled-resource", "revision_id": "e1fb3ea3-44b2-4dc0-94f6-b09e828142d2", "id": "5a4de3fd-7a3d-4bfb-9bf6-e37630c6dc01"}, {"package_id": "b1f2f7be-d024-425f-b6ff-5d8f45d86738", "value": "[{\"type\": \"revision\", \"value\": \"2015-02-10\"}]", "revision_timestamp": "2015-02-10T14:40:05.686705", "state": "active", "key": "dataset-reference-date", "revision_id": "e1fb3ea3-44b2-4dc0-94f6-b09e828142d2", "id": "e45d14d0-e851-489f-9ef1-fea26f6e9821"}, {"package_id": "b1f2f7be-d024-425f-b6ff-5d8f45d86738", "value": "asNeeded", "revision_timestamp": "2015-02-10T14:40:05.686705", "state": "active", "key": "frequency-of-update", "revision_id": "e1fb3ea3-44b2-4dc0-94f6-b09e828142d2", "id": "4ddb1bfc-f3e3-4a00-9a03-24645688a6e3"}, {"package_id": "b1f2f7be-d024-425f-b6ff-5d8f45d86738", "value": "25361192-b257-4b8b-9cb0-8dc80b3626ba", "revision_timestamp": "2015-02-10T14:40:05.686705", "state": "active", "key": "guid", "revision_id": "e1fb3ea3-44b2-4dc0-94f6-b09e828142d2", "id": "cd0a56d6-a4bb-4b6a-b41e-65bad367172f"}, {"package_id": "b1f2f7be-d024-425f-b6ff-5d8f45d86738", "value": "d9c77a1e-4573-4ccf-80f4-dcd4e023bffe", "revision_timestamp": "2015-02-10T14:40:05.686705", "state": "active", "key": "harvest_object_id", "revision_id": "e1fb3ea3-44b2-4dc0-94f6-b09e828142d2", "id": "bc77aad6-4a27-4f50-8a60-ba920acc62c2"}, {"package_id": "b1f2f7be-d024-425f-b6ff-5d8f45d86738", "value": "http://inspire.misoportal.com/metadata/files/Adur_and_Worthing_Council/adur_allotments.xml", "revision_timestamp": "2015-02-10T14:40:05.686705", "state": "active", "key": "harvest_source_reference", "revision_id": "e1fb3ea3-44b2-4dc0-94f6-b09e828142d2", "id": "673d686d-b010-4637-84d1-2caf9aca1332"}, {"package_id": "b1f2f7be-d024-425f-b6ff-5d8f45d86738", "value": "harvest", "revision_timestamp": "2015-02-10T14:40:05.686705", "state": "active", "key": "import_source", "revision_id": "e1fb3ea3-44b2-4dc0-94f6-b09e828142d2", "id": "847d5f05-02bf-4372-b2b3-fc7131edce80"}, {"package_id": "b1f2f7be-d024-425f-b6ff-5d8f45d86738", "value": "[\"geossNonCommercial\", \"(e) intellectual property rights\", \"no limitation\"]", "revision_timestamp": "2015-02-10T14:40:05.686705", "state": "active", "key": "licence", "revision_id": "e1fb3ea3-44b2-4dc0-94f6-b09e828142d2", "id": "00252dea-a771-41e2-b108-0b583448b130"}, {"package_id": "b1f2f7be-d024-425f-b6ff-5d8f45d86738", "value": "2015-02-10", "revision_timestamp": "2015-02-10T14:40:05.686705", "state": "active", "key": "metadata-date", "revision_id": "e1fb3ea3-44b2-4dc0-94f6-b09e828142d2", "id": "d2d676dc-3569-436a-b86d-150cc3ad870d"}, {"package_id": "b1f2f7be-d024-425f-b6ff-5d8f45d86738", "value": "eng", "revision_timestamp": "2015-02-10T14:40:05.686705", "state": "active", "key": "metadata-language", "revision_id": "e1fb3ea3-44b2-4dc0-94f6-b09e828142d2", "id": "2f1618e3-847a-49c4-8932-bbfcf37e22e6"}, {"package_id": "b1f2f7be-d024-425f-b6ff-5d8f45d86738", "value": "", "revision_timestamp": "2015-02-10T14:40:05.686705", "state": "active", "key": "provider", "revision_id": "e1fb3ea3-44b2-4dc0-94f6-b09e828142d2", "id": "a80208a1-d383-40ad-b299-60c03388f4fc"}, {"package_id": "b1f2f7be-d024-425f-b6ff-5d8f45d86738", "value": "dataset", "revision_timestamp": "2015-02-10T14:40:05.686705", "state": "active", "key": "resource-type", "revision_id": "e1fb3ea3-44b2-4dc0-94f6-b09e828142d2", "id": "df7e4536-7a72-436d-ad76-e5284c0640e4"}, {"package_id": "b1f2f7be-d024-425f-b6ff-5d8f45d86738", "value": "Adur District and Worthing Borough Councils (pointOfContact)", "revision_timestamp": "2015-02-10T14:40:05.686705", "state": "active", "key": "responsible-party", "revision_id": "e1fb3ea3-44b2-4dc0-94f6-b09e828142d2", "id": "f7a152de-a339-4e84-9a69-ee900eaf1788"}, {"package_id": "b1f2f7be-d024-425f-b6ff-5d8f45d86738", "value": "{\"type\":\"Polygon\",\"coordinates\":[[[-0.222355168468641, 50.817007994021],[-0.222355168468641, 50.8437840950851], [-0.434271074180314, 50.8437840950851], [-0.434271074180314, 50.817007994021], [-0.222355168468641, 50.817007994021]]]}", "revision_timestamp": "2015-02-10T14:40:05.686705", "state": "active", "key": "spatial", "revision_id": "e1fb3ea3-44b2-4dc0-94f6-b09e828142d2", "id": "996df7fa-cd2e-4a5d-b7ea-cc31d182be2d"}, {"package_id": "b1f2f7be-d024-425f-b6ff-5d8f45d86738", "value": "", "revision_timestamp": "2015-02-10T14:40:05.686705", "state": "active", "key": "spatial-data-service-type", "revision_id": "e1fb3ea3-44b2-4dc0-94f6-b09e828142d2", "id": "724ed8b9-29bb-4407-aa92-0634af31f436"}, {"package_id": "b1f2f7be-d024-425f-b6ff-5d8f45d86738", "value": "", "revision_timestamp": "2015-02-10T14:40:05.686705", "state": "active", "key": "spatial-reference-system", "revision_id": "e1fb3ea3-44b2-4dc0-94f6-b09e828142d2", "id": "8ef19f45-e4c5-4945-b4d1-c8254b35d989"}, {"package_id": "b1f2f7be-d024-425f-b6ff-5d8f45d86738", "value": "[]", "revision_timestamp": "2015-02-10T14:40:05.686705", "state": "active", "key": "temporal_coverage-from", "revision_id": "e1fb3ea3-44b2-4dc0-94f6-b09e828142d2", "id": "84c3ac74-2473-4dc3-b508-26a9a083edf5"}, {"package_id": "b1f2f7be-d024-425f-b6ff-5d8f45d86738", "value": "[]", "revision_timestamp": "2015-02-10T14:40:05.686705", "state": "active", "key": "temporal_coverage-to", "revision_id": "e1fb3ea3-44b2-4dc0-94f6-b09e828142d2", "id": "c4ca2cd3-5740-4b00-add8-665ff3767a16"}, {"package_id": "b1f2f7be-d024-425f-b6ff-5d8f45d86738", "value": "Towns & Cities", "revision_timestamp": "2015-03-16T18:10:08.802815", "state": "active", "key": "theme-primary", "revision_id": "fc2b6630-84f8-4c88-8ac7-0ca275b2bc97", "id": "77d8ce2e-3141-4dbf-992a-3af069deb520"}, {"package_id": "b1f2f7be-d024-425f-b6ff-5d8f45d86738", "value": "[\"Business & Economy\"]", "revision_timestamp": "2015-03-16T18:10:08.802815", "state": "active", "key": "theme-secondary", "revision_id": "fc2b6630-84f8-4c88-8ac7-0ca275b2bc97", "id": "65f4d855-14f2-4991-af1f-bed302a30f39"}], "individual_resources": [{"verified_date": "2015-02-10T14:40:05.328921", "hash": "", "description": "Resource locator", "created": "2015-02-10T14:40:05.752325", "url": "http://inspire.misoportal.com/geoserver/adur_and_worthing_council_allotments/wms?request=getCapabilities", "format": "wms", "verified": "True", "tracking_summary": {"total": 0, "recent": 0}, "resource_locator_function": "information", "resource_locator_protocol": "", "ckan_recommended_wms_preview": "True", "position": 0, "revision_id": "e1fb3ea3-44b2-4dc0-94f6-b09e828142d2", "wms_base_urls": "http://inspire.misoportal.com:80/geoserver/adur_and_worthing_council_allotments/ows", "id": "da6e91fe-4fe7-4442-9382-4ac5a402bada", "name": "INSPIRE View Service"}, {"hash": "", "description": "Resource locator", "created": "2015-02-10T14:40:05.752341", "url": "http://inspire.misoportal.com/geoserver/adur_and_worthing_council_allotments/wfs?service=wfs&version=2.0.0&request=GetCapabilities", "format": "", "tracking_summary": {"total": 0, "recent": 0}, "resource_locator_function": "download", "resource_locator_protocol": "", "position": 1, "revision_id": "e1fb3ea3-44b2-4dc0-94f6-b09e828142d2", "id": "8aeee900-3a8a-4f8c-b636-162886a43e2a", "name": "INSPIRE Download Service"}], "title": "Allotments", "revision_id": "e1fb3ea3-44b2-4dc0-94f6-b09e828142d2", "theme-primary": "Towns & Cities"}}